anoctor/icons/bmw.ico
anoctor/icons/bmw.jpg
anoctor/src/__init__.py
anoctor/src/anomaly_detector.py
anoctor/venv/Lib/site-packages/easy_install.py
anoctor/venv/Lib/site-packages/pip/__init__.py
anoctor/venv/Lib/site-packages/pip/__main__.py
anoctor/venv/Lib/site-packages/pip/_internal/__init__.py
anoctor/venv/Lib/site-packages/pip/_internal/build_env.py
anoctor/venv/Lib/site-packages/pip/_internal/cache.py
anoctor/venv/Lib/site-packages/pip/_internal/cli/__init__.py
anoctor/venv/Lib/site-packages/pip/_internal/cli/autocompletion.py
anoctor/venv/Lib/site-packages/pip/_internal/cli/base_command.py
anoctor/venv/Lib/site-packages/pip/_internal/cli/cmdoptions.py
anoctor/venv/Lib/site-packages/pip/_internal/cli/main_parser.py
anoctor/venv/Lib/site-packages/pip/_internal/cli/parser.py
anoctor/venv/Lib/site-packages/pip/_internal/cli/status_codes.py
anoctor/venv/Lib/site-packages/pip/_internal/commands/__init__.py
anoctor/venv/Lib/site-packages/pip/_internal/commands/check.py
anoctor/venv/Lib/site-packages/pip/_internal/commands/completion.py
anoctor/venv/Lib/site-packages/pip/_internal/commands/configuration.py
anoctor/venv/Lib/site-packages/pip/_internal/commands/debug.py
anoctor/venv/Lib/site-packages/pip/_internal/commands/download.py
anoctor/venv/Lib/site-packages/pip/_internal/commands/freeze.py
anoctor/venv/Lib/site-packages/pip/_internal/commands/hash.py
anoctor/venv/Lib/site-packages/pip/_internal/commands/help.py
anoctor/venv/Lib/site-packages/pip/_internal/commands/install.py
anoctor/venv/Lib/site-packages/pip/_internal/commands/list.py
anoctor/venv/Lib/site-packages/pip/_internal/commands/search.py
anoctor/venv/Lib/site-packages/pip/_internal/commands/show.py
anoctor/venv/Lib/site-packages/pip/_internal/commands/uninstall.py
anoctor/venv/Lib/site-packages/pip/_internal/commands/wheel.py
anoctor/venv/Lib/site-packages/pip/_internal/configuration.py
anoctor/venv/Lib/site-packages/pip/_internal/distributions/__init__.py
anoctor/venv/Lib/site-packages/pip-19.2.3.dist-info/entry_points.txt
anoctor/venv/Lib/site-packages/pip-19.2.3.dist-info/INSTALLER
anoctor/venv/Lib/site-packages/pip-19.2.3.dist-info/LICENSE.txt
anoctor/venv/Lib/site-packages/pip-19.2.3.dist-info/METADATA
anoctor/venv/Lib/site-packages/pip-19.2.3.dist-info/RECORD
anoctor/venv/Lib/site-packages/pip-19.2.3.dist-info/top_level.txt
anoctor/venv/Lib/site-packages/pip-19.2.3.dist-info/WHEEL
anoctor/venv/Lib/site-packages/setuptools-41.2.0.dist-info/dependency_links.txt
anoctor/venv/Lib/site-packages/setuptools-41.2.0.dist-info/entry_points.txt
anoctor/venv/Lib/site-packages/setuptools-41.2.0.dist-info/INSTALLER
anoctor/venv/Lib/site-packages/setuptools-41.2.0.dist-info/LICENSE
anoctor/venv/Lib/site-packages/setuptools-41.2.0.dist-info/METADATA
anoctor/venv/Lib/site-packages/setuptools-41.2.0.dist-info/RECORD
anoctor/venv/Lib/site-packages/setuptools-41.2.0.dist-info/top_level.txt
anoctor/venv/Lib/site-packages/setuptools-41.2.0.dist-info/WHEEL
anoctor/venv/Lib/site-packages/setuptools-41.2.0.dist-info/zip-safe
anoctor-0.1.0.dist-info/LICENSE
anoctor-0.1.0.dist-info/METADATA
anoctor-0.1.0.dist-info/WHEEL
anoctor-0.1.0.dist-info/RECORD
