Metadata-Version: 2.1
Name: anoctor
Version: 0.1.0
Summary: Anomaly Detection for BMW Charging Signals
License: BMW AG
Author: Abhijith Narayanan
Requires-Python: >=3.7,<4.0
Classifier: License :: Other/Proprietary License
Classifier: Programming Language :: Python :: 3
Classifier: Programming Language :: Python :: 3.7
Classifier: Programming Language :: Python :: 3.8
Classifier: Programming Language :: Python :: 3.9
Classifier: Programming Language :: Python :: 3.10
Classifier: Programming Language :: Python :: 3.11
Requires-Dist: PySimpleGUI (>=4.60.5,<5.0.0)
Requires-Dist: joblib (>=1.3.2,<2.0.0)
Requires-Dist: keras (>=2.11.0,<3.0.0)
Requires-Dist: matplotlib (>=3.4.0,<4.0.0)
Requires-Dist: numpy (>=1.16.0,<2.0.0)
Requires-Dist: pandas (>=0.25.0,<0.26.0)
Requires-Dist: pathlib (>=1.0.1,<2.0.0)
Requires-Dist: seaborn (>=0.12.1,<0.13.0)
Requires-Dist: sklearn (>=0.0.post12,<0.1)
Requires-Dist: tensorflow (>=1.13.1.post1,<2.0.0)
